crime_sim_toolkit/__init__.py
crime_sim_toolkit/initialiser.py
crime_sim_toolkit/microsim.py
crime_sim_toolkit/poisson_sim.py
crime_sim_toolkit/utils.py
crime_sim_toolkit/vis_utils.py
crime_sim_toolkit/output/.gitkeep
crime_sim_toolkit/output/test.html
crime_sim_toolkit/src/CrimeCatMappings.csv
crime_sim_toolkit/src/prc-pfa-201718_new.csv
crime_sim_toolkit/src/simple_policeuk_perc_offence.csv
crime_sim_toolkit/src/LSOA_data/PoliceforceLSOA.csv
crime_sim_toolkit/src/LSOA_data/census_2011_population_hh.csv
crime_sim_toolkit/tests/__init__.py
crime_sim_toolkit/tests/initialiser_test.py
crime_sim_toolkit/tests/microsim_test.py
crime_sim_toolkit/tests/test_all.py
crime_sim_toolkit/tests/test_utils.py
crime_sim_toolkit/tests/util_test.py
crime_sim_toolkit/tests/vis_util_test.py
crime_sim_toolkit/tests/testing_data/data_to_map.csv
crime_sim_toolkit/tests/testing_data/match_LSOA_test.csv
crime_sim_toolkit/tests/testing_data/random_date1.csv
crime_sim_toolkit/tests/testing_data/random_date2.csv
crime_sim_toolkit/tests/testing_data/report_2_counts.csv
crime_sim_toolkit/tests/testing_data/reverse_Crimedescription_test.csv
crime_sim_toolkit/tests/testing_data/test_1.json
crime_sim_toolkit/tests/testing_data/test_2.json
crime_sim_toolkit/tests/testing_data/test_aggoobDay_data.csv
crime_sim_toolkit/tests/testing_data/test_aggoobdata.csv
crime_sim_toolkit/tests/testing_data/test_aggtrainDay_data.csv
crime_sim_toolkit/tests/testing_data/test_aggtraindata.csv
crime_sim_toolkit/tests/testing_data/test_counts1.csv
crime_sim_toolkit/tests/testing_data/test_oobDay_data.csv
crime_sim_toolkit/tests/testing_data/test_oobdata.csv
crime_sim_toolkit/tests/testing_data/test_oobsplit.csv
crime_sim_toolkit/tests/testing_data/test_sample_perturb.csv
crime_sim_toolkit/tests/testing_data/test_trainDay_data.csv
crime_sim_toolkit/tests/testing_data/test_traindata.csv
crime_sim_toolkit/tests/testing_data/test_microsim/sample_seed_pop.csv
crime_sim_toolkit-1.5.0.dist-info/LICENSE
crime_sim_toolkit-1.5.0.dist-info/METADATA
crime_sim_toolkit-1.5.0.dist-info/WHEEL
crime_sim_toolkit-1.5.0.dist-info/top_level.txt
crime_sim_toolkit-1.5.0.dist-info/RECORD
