Metadata-Version: 2.1
Name: crime-sim-toolkit
Version: 1.5.0
Summary: A toolkit for simulating UK crime data.
Home-page: https://github.com/Sparrow0hawk/crime_sim_toolkit
Author: Alex Coleman
Author-email: a.coleman1@leeds.ac.uk
License: MIT License
Platform: UNKNOWN
Requires-Python: >=3.6
